LICENSE
README.md
setup.py
NorenRestApiPy/NorenApi.py
NorenRestApiPy/__init__.py
NorenRestApiPytest.egg-info/PKG-INFO
NorenRestApiPytest.egg-info/SOURCES.txt
NorenRestApiPytest.egg-info/dependency_links.txt
NorenRestApiPytest.egg-info/top_level.txt