Metadata-Version: 2.1
Name: NorenRestApiPytest
Version: 0.0.22
Summary: A package for NorenOMS
Author: KumarAnand
Author-email: kumar.anand@kambala.co.in
Classifier: Programming Language :: Python :: 3
Classifier: License :: Other/Proprietary License
Classifier: Operating System :: OS Independent
License-File: LICENSE
